LICENSE.txt
MANIFEST.in
README.rst
requirements.txt
setup.py
./ldpatch/__init__.py
./ldpatch/processor.py
./ldpatch/syntax.py
bin/ldpatch-apply
ldpatch.egg-info/PKG-INFO
ldpatch.egg-info/SOURCES.txt
ldpatch.egg-info/dependency_links.txt
ldpatch.egg-info/requires.txt
ldpatch.egg-info/top_level.txt