Metadata-Version: 1.0
Name: ldpatch
Version: 0.9
Summary: A kernel for trace-based systems
Home-page: http://github.com/pchampin/ld-patch-py
Author: Pierre-Antoine Champin
Author-email: pchampin@liris.cnrs.fr
License: LGPL v3
Platform: OS Independant
